gmsh4mrst/__init__.py
gmsh4mrst/_arguments.py
gmsh4mrst/_assertions.py
gmsh4mrst/_geometry.py
gmsh4mrst/_gmsh.py
gmsh4mrst/background_grid_2D.py
gmsh4mrst/delaunay_grid_2D.py
gmsh4mrst/pebi_base_2D.py
gmsh4mrst-1.0.0.dist-info/LICENCE
gmsh4mrst-1.0.0.dist-info/METADATA
gmsh4mrst-1.0.0.dist-info/WHEEL
gmsh4mrst-1.0.0.dist-info/top_level.txt
gmsh4mrst-1.0.0.dist-info/RECORD
