Metadata-Version: 2.1
Name: gmsh4mrst
Version: 1.0.0
Summary: Gmsh backend integration for MRST
Home-page: https://github.com/BollaBerg/gmsh4mrst
Author: Andreas Bjelland Berg
Author-email: berg.andreasb+PyPi@gmail.com
Project-URL: Bug Tracker, https://github.com/BollaBerg/gmsh4mrst/issues
Classifier: Programming Language :: Python :: 3
Classifier: License :: OSI Approved :: GNU General Public License v3 (GPLv3)
Classifier: Operating System :: OS Independent
Classifier: Development Status :: 3 - Alpha
Classifier: Intended Audience :: Science/Research
Classifier: Topic :: Scientific/Engineering
Classifier: Topic :: Scientific/Engineering :: Physics
Requires-Python: >=3.8
License-File: LICENCE
Requires-Dist: gmsh (>=4.10)
